{
    "errors": [],
    "fails": [],
    "findings": [
        {
            "filename": "/home/shuo/repo/cgt/runtime/71c7ad89400a1388590d298694a5df34.rt.hex",
            "name": "Callstack Depth Attack Vulnerability"
        },
        {
            "filename": "/home/shuo/repo/cgt/runtime/71c7ad89400a1388590d298694a5df34.rt.hex",
            "name": "Transaction-Ordering Dependence (TOD)"
        }
    ],
    "infos": [],
    "parser": {
        "id": "oyente",
        "mode": "runtime",
        "version": "2023/02/27"
    }
}
