{
    "errors": [],
    "fails": [],
    "findings": [
        {
            "filename": "/home/shuo/repo/cgt/runtime/51f25571a1d2b7a927cb1e6f01d7730b.rt.hex",
            "name": "Timestamp Dependency"
        },
        {
            "filename": "/home/shuo/repo/cgt/runtime/51f25571a1d2b7a927cb1e6f01d7730b.rt.hex",
            "name": "Transaction-Ordering Dependence (TOD)"
        }
    ],
    "infos": [],
    "parser": {
        "id": "oyente",
        "mode": "runtime",
        "version": "2023/02/27"
    }
}
