{
    "errors": [],
    "fails": [],
    "findings": [
        {
            "filename": "/home/shuo/repo/cgt/runtime/5c9e766e1f284d31e9d5558c71b6c844.rt.hex",
            "name": "Re-Entrancy Vulnerability"
        },
        {
            "filename": "/home/shuo/repo/cgt/runtime/5c9e766e1f284d31e9d5558c71b6c844.rt.hex",
            "name": "Transaction-Ordering Dependence (TOD)"
        }
    ],
    "infos": [],
    "parser": {
        "id": "oyente",
        "mode": "runtime",
        "version": "2023/02/27"
    }
}
